{
    "Popular": [
        {
            "id": 1,
            "Img": "../../asset/Chicken_tikka.png",
            "unsaved": "../../asset/unsaved.png",
            "rating": "../../asset/rating.png",
            "calorie":"501 kcal"
         },
        {
            "id": 2,
            "Img": "../../asset/Avacado_toast.png",
            "unsaved": "../../asset/unsaved.png",
            "rating": "../../asset/rating.png",
            "calorie":"501 kcal"
         },
        {
            "id": 3,
            "Img": "../../asset/omlette_roll.png",
            "unsaved": "../../asset/unsaved.png",
            "rating": "../../asset/rating.png",
            "calorie":"501 kcal"
         }
        ],
    
         "Loved":[
        {
            "id": 4,
            "Img": "../../asset/Nutty.png",
            "unsaved": "../../asset/unsaved.png",
            "rating": "../../asset/rating.png",
            "calorie":"501 kcal"
         },
        {
            "id":5,
            "Img": "../../asset/oats.png",
            "unsaved": "../../asset/unsaved.png",
            "star": "../../asset/rating.png",
            "calorie":"501 kcal"
         },
        {
            "id": 6,
            "Img": "../../asset/Pesto_pasta.png",
            "unsaved": "../../asset/unsaved.png",
            "rating": "../../asset/rating.png",
            "calorie":"501 kcal"
        },
        {
            "id": 7,
            "Img": "../../asset/Chicken_tikka.png",
            "unsaved": "../../asset/unsaved.png",
            "rating": "../../asset/rating.png",
            "calorie":"501 kcal"
         },
        {
            "id": 8,
            "Img": "../../asset/Avacado_toast.png",
            "unsaved": "../../asset/unsaved.png",
            "rating": "../../asset/rating.png",
            "calorie":"501 kcal"
         },
        {
            "id": 9,
            "Img": "../../asset/omlette_roll.png",
            "unsaved": "../../asset/unsaved.png",
            "rating": "../../asset/rating.png",
            "calorie":"501 kcal"
         }
    ]
}